zoetrope/__init__.py
zoetrope/zoetrope.py
zoetrope/templates/__init__.py
zoetrope/templates/unittest_template.py
zoetrope-0.2.data/scripts/zoetrope
zoetrope-0.2.dist-info/METADATA
zoetrope-0.2.dist-info/WHEEL
zoetrope-0.2.dist-info/pbr.json
zoetrope-0.2.dist-info/top_level.txt
zoetrope-0.2.dist-info/RECORD
