Metadata-Version: 2.1
Name: zoetrope
Version: 0.2
Summary: A templating tool that creates unit tests from an arbitrary file.
Home-page: UNKNOWN
License: UNKNOWN
Platform: UNKNOWN
Requires-Python: ~=3.6
Requires-Dist: mock
